LICENSE
MANIFEST.in
README.rst
buildout.cfg
develop.cfg
pyproject.toml
requirements.txt
setup.py
version.txt
bob/__init__.py
bob.ap.egg-info/PKG-INFO
bob.ap.egg-info/SOURCES.txt
bob.ap.egg-info/dependency_links.txt
bob.ap.egg-info/not-zip-safe
bob.ap.egg-info/requires.txt
bob.ap.egg-info/top_level.txt
bob/ap/__init__.py
bob/ap/ceps.cpp
bob/ap/energy.cpp
bob/ap/frame_extractor.cpp
bob/ap/main.cpp
bob/ap/spectrogram.cpp
bob/ap/test_ceps.py
bob/ap/test_energy.py
bob/ap/test_spectrogram.py
bob/ap/test_utils.py
bob/ap/types.h
bob/ap/version.cpp
bob/ap/cpp/Ceps.cpp
bob/ap/cpp/Energy.cpp
bob/ap/cpp/FrameExtractor.cpp
bob/ap/cpp/Spectrogram.cpp
bob/ap/data/sample.wav
bob/ap/include/bob.ap/Ceps.h
bob/ap/include/bob.ap/Energy.h
bob/ap/include/bob.ap/FrameExtractor.h
bob/ap/include/bob.ap/Spectrogram.h
bob/ap/include/bob.ap/config.h
doc/conf.py
doc/guide.rst
doc/index.rst
doc/links.rst
doc/py_api.rst